poc_whl/__init__.py
poc_whl/case.py
poc_whl-1.0.dist-info/METADATA
poc_whl-1.0.dist-info/WHEEL
poc_whl-1.0.dist-info/top_level.txt
poc_whl-1.0.dist-info/RECORD
