Metadata-Version: 2.1
Name: poc_whl
Version: 1.0
Requires-Python: >=3.6
Requires-Dist: fastapi>=0.68.0
Requires-Dist: uvicorn>=0.15.0
